repaneii/__init__.py
repaneii/dom.py
repaneii/expr.py
repaneii/mesh.py
repaneii/repaneii.cp310-win_amd64.pyd
repaneii-0.1.2.data/data/README/README.md
repaneii-0.1.2.data/data/licenses/APACHE2
repaneii-0.1.2.data/data/licenses/MIT
repaneii-0.1.2.dist-info/LICENSE
repaneii-0.1.2.dist-info/METADATA
repaneii-0.1.2.dist-info/WHEEL
repaneii-0.1.2.dist-info/top_level.txt
repaneii-0.1.2.dist-info/RECORD
